{
  "version": "2.3.6",
  "flags": {},
  "shapes": [
    {
      "text": "",
      "label": "xinpian",
      "points": [
        [
          1037.0,
          177.0
        ],
        [
          1037.0,
          178.0
        ],
        [
          1037.0,
          179.0
        ],
        [
          1037.0,
          180.0
        ],
        [
          1037.0,
          181.0
        ],
        [
          1037.0,
          182.0
        ],
        [
          1037.0,
          183.0
        ],
        [
          1037.0,
          184.0
        ],
        [
          1037.0,
          185.0
        ],
        [
          1037.0,
          186.0
        ],
        [
          1037.0,
          187.0
        ],
        [
          1037.0,
          188.0
        ],
        [
          1037.0,
          189.0
        ],
        [
          1037.0,
          190.0
        ],
        [
          1037.0,
          191.0
        ],
        [
          1037.0,
          192.0
        ],
        [
          1037.0,
          193.0
        ],
        [
          1037.0,
          194.0
        ],
        [
          1037.0,
          195.0
        ],
        [
          1037.0,
          196.0
        ],
        [
          1037.0,
          197.0
        ],
        [
          1037.0,
          198.0
        ],
        [
          1037.0,
          199.0
        ],
        [
          1037.0,
          200.0
        ],
        [
          1037.0,
          201.0
        ],
        [
          1037.0,
          202.0
        ],
        [
          1037.0,
          203.0
        ],
        [
          1037.0,
          204.0
        ],
        [
          1037.0,
          205.0
        ],
        [
          1037.0,
          206.0
        ],
        [
          1037.0,
          207.0
        ],
        [
          1037.0,
          208.0
        ],
        [
          1037.0,
          209.0
        ],
        [
          1037.0,
          210.0
        ],
        [
          1037.0,
          211.0
        ],
        [
          1037.0,
          212.0
        ],
        [
          1037.0,
          213.0
        ],
        [
          1037.0,
          214.0
        ],
        [
          1037.0,
          215.0
        ],
        [
          1037.0,
          216.0
        ],
        [
          1037.0,
          217.0
        ],
        [
          1037.0,
          218.0
        ],
        [
          1037.0,
          219.0
        ],
        [
          1037.0,
          220.0
        ],
        [
          1037.0,
          221.0
        ],
        [
          1037.0,
          222.0
        ],
        [
          1037.0,
          223.0
        ],
        [
          1037.0,
          224.0
        ],
        [
          1037.0,
          225.0
        ],
        [
          1037.0,
          226.0
        ],
        [
          1037.0,
          227.0
        ],
        [
          1037.0,
          228.0
        ],
        [
          1037.0,
          229.0
        ],
        [
          1037.0,
          230.0
        ],
        [
          1037.0,
          231.0
        ],
        [
          1037.0,
          232.0
        ],
        [
          1037.0,
          233.0
        ],
        [
          1037.0,
          234.0
        ],
        [
          1037.0,
          235.0
        ],
        [
          1037.0,
          236.0
        ],
        [
          1038.0,
          236.0
        ],
        [
          1039.0,
          236.0
        ],
        [
          1040.0,
          236.0
        ],
        [
          1041.0,
          236.0
        ],
        [
          1042.0,
          236.0
        ],
        [
          1043.0,
          236.0
        ],
        [
          1044.0,
          236.0
        ],
        [
          1045.0,
          236.0
        ],
        [
          1046.0,
          236.0
        ],
        [
          1047.0,
          236.0
        ],
        [
          1048.0,
          236.0
        ],
        [
          1049.0,
          236.0
        ],
        [
          1050.0,
          236.0
        ],
        [
          1051.0,
          236.0
        ],
        [
          1052.0,
          236.0
        ],
        [
          1053.0,
          236.0
        ],
        [
          1054.0,
          236.0
        ],
        [
          1055.0,
          236.0
        ],
        [
          1056.0,
          236.0
        ],
        [
          1057.0,
          236.0
        ],
        [
          1058.0,
          236.0
        ],
        [
          1059.0,
          236.0
        ],
        [
          1060.0,
          236.0
        ],
        [
          1061.0,
          236.0
        ],
        [
          1062.0,
          236.0
        ],
        [
          1063.0,
          236.0
        ],
        [
          1064.0,
          236.0
        ],
        [
          1065.0,
          236.0
        ],
        [
          1066.0,
          236.0
        ],
        [
          1067.0,
          236.0
        ],
        [
          1068.0,
          236.0
        ],
        [
          1069.0,
          236.0
        ],
        [
          1070.0,
          236.0
        ],
        [
          1071.0,
          236.0
        ],
        [
          1072.0,
          236.0
        ],
        [
          1073.0,
          236.0
        ],
        [
          1074.0,
          236.0
        ],
        [
          1075.0,
          236.0
        ],
        [
          1076.0,
          236.0
        ],
        [
          1077.0,
          236.0
        ],
        [
          1078.0,
          236.0
        ],
        [
          1079.0,
          236.0
        ],
        [
          1080.0,
          236.0
        ],
        [
          1081.0,
          236.0
        ],
        [
          1082.0,
          236.0
        ],
        [
          1083.0,
          236.0
        ],
        [
          1084.0,
          236.0
        ],
        [
          1085.0,
          236.0
        ],
        [
          1086.0,
          236.0
        ],
        [
          1087.0,
          236.0
        ],
        [
          1088.0,
          236.0
        ],
        [
          1089.0,
          236.0
        ],
        [
          1090.0,
          236.0
        ],
        [
          1091.0,
          236.0
        ],
        [
          1092.0,
          236.0
        ],
        [
          1093.0,
          236.0
        ],
        [
          1094.0,
          236.0
        ],
        [
          1094.0,
          235.0
        ],
        [
          1094.0,
          234.0
        ],
        [
          1094.0,
          233.0
        ],
        [
          1094.0,
          232.0
        ],
        [
          1094.0,
          231.0
        ],
        [
          1094.0,
          230.0
        ],
        [
          1094.0,
          229.0
        ],
        [
          1094.0,
          228.0
        ],
        [
          1094.0,
          227.0
        ],
        [
          1094.0,
          226.0
        ],
        [
          1094.0,
          225.0
        ],
        [
          1094.0,
          224.0
        ],
        [
          1094.0,
          223.0
        ],
        [
          1094.0,
          222.0
        ],
        [
          1094.0,
          221.0
        ],
        [
          1094.0,
          220.0
        ],
        [
          1094.0,
          219.0
        ],
        [
          1094.0,
          218.0
        ],
        [
          1094.0,
          217.0
        ],
        [
          1094.0,
          216.0
        ],
        [
          1094.0,
          215.0
        ],
        [
          1094.0,
          214.0
        ],
        [
          1094.0,
          213.0
        ],
        [
          1094.0,
          212.0
        ],
        [
          1094.0,
          211.0
        ],
        [
          1094.0,
          210.0
        ],
        [
          1094.0,
          209.0
        ],
        [
          1094.0,
          208.0
        ],
        [
          1094.0,
          207.0
        ],
        [
          1094.0,
          206.0
        ],
        [
          1094.0,
          205.0
        ],
        [
          1094.0,
          204.0
        ],
        [
          1094.0,
          203.0
        ],
        [
          1094.0,
          202.0
        ],
        [
          1094.0,
          201.0
        ],
        [
          1094.0,
          200.0
        ],
        [
          1094.0,
          199.0
        ],
        [
          1094.0,
          198.0
        ],
        [
          1094.0,
          197.0
        ],
        [
          1094.0,
          196.0
        ],
        [
          1094.0,
          195.0
        ],
        [
          1094.0,
          194.0
        ],
        [
          1094.0,
          193.0
        ],
        [
          1094.0,
          192.0
        ],
        [
          1094.0,
          191.0
        ],
        [
          1094.0,
          190.0
        ],
        [
          1094.0,
          189.0
        ],
        [
          1094.0,
          188.0
        ],
        [
          1094.0,
          187.0
        ],
        [
          1094.0,
          186.0
        ],
        [
          1094.0,
          185.0
        ],
        [
          1094.0,
          184.0
        ],
        [
          1094.0,
          183.0
        ],
        [
          1094.0,
          182.0
        ],
        [
          1094.0,
          181.0
        ],
        [
          1094.0,
          180.0
        ],
        [
          1094.0,
          179.0
        ],
        [
          1094.0,
          178.0
        ],
        [
          1094.0,
          177.0
        ],
        [
          1093.0,
          177.0
        ],
        [
          1092.0,
          177.0
        ],
        [
          1091.0,
          177.0
        ],
        [
          1090.0,
          177.0
        ],
        [
          1089.0,
          177.0
        ],
        [
          1088.0,
          177.0
        ],
        [
          1087.0,
          177.0
        ],
        [
          1086.0,
          177.0
        ],
        [
          1085.0,
          177.0
        ],
        [
          1084.0,
          177.0
        ],
        [
          1083.0,
          177.0
        ],
        [
          1082.0,
          177.0
        ],
        [
          1081.0,
          177.0
        ],
        [
          1080.0,
          177.0
        ],
        [
          1079.0,
          177.0
        ],
        [
          1078.0,
          177.0
        ],
        [
          1077.0,
          177.0
        ],
        [
          1076.0,
          177.0
        ],
        [
          1075.0,
          177.0
        ],
        [
          1074.0,
          177.0
        ],
        [
          1073.0,
          177.0
        ],
        [
          1072.0,
          177.0
        ],
        [
          1071.0,
          177.0
        ],
        [
          1070.0,
          177.0
        ],
        [
          1069.0,
          177.0
        ],
        [
          1068.0,
          177.0
        ],
        [
          1067.0,
          177.0
        ],
        [
          1066.0,
          177.0
        ],
        [
          1065.0,
          177.0
        ],
        [
          1064.0,
          177.0
        ],
        [
          1063.0,
          177.0
        ],
        [
          1062.0,
          177.0
        ],
        [
          1061.0,
          177.0
        ],
        [
          1060.0,
          177.0
        ],
        [
          1059.0,
          177.0
        ],
        [
          1058.0,
          177.0
        ],
        [
          1057.0,
          177.0
        ],
        [
          1056.0,
          177.0
        ],
        [
          1055.0,
          177.0
        ],
        [
          1054.0,
          177.0
        ],
        [
          1053.0,
          177.0
        ],
        [
          1052.0,
          177.0
        ],
        [
          1051.0,
          177.0
        ],
        [
          1050.0,
          177.0
        ],
        [
          1049.0,
          177.0
        ],
        [
          1048.0,
          177.0
        ],
        [
          1047.0,
          177.0
        ],
        [
          1046.0,
          177.0
        ],
        [
          1045.0,
          177.0
        ],
        [
          1044.0,
          177.0
        ],
        [
          1043.0,
          177.0
        ],
        [
          1042.0,
          177.0
        ],
        [
          1041.0,
          177.0
        ],
        [
          1040.0,
          177.0
        ],
        [
          1039.0,
          177.0
        ],
        [
          1038.0,
          177.0
        ]
      ],
      "group_id": null,
      "description": null,
      "difficult": false,
      "shape_type": "polygon",
      "flags": {},
      "attributes": {}
    },
    {
      "label": "zazhi",
      "points": [
        [
          422.0,
          229.0
        ],
        [
          419.0,
          229.0
        ],
        [
          418.0,
          230.0
        ],
        [
          417.0,
          230.0
        ],
        [
          413.0,
          234.0
        ],
        [
          413.0,
          235.0
        ],
        [
          412.0,
          236.0
        ],
        [
          412.0,
          237.0
        ],
        [
          411.0,
          238.0
        ],
        [
          411.0,
          249.0
        ],
        [
          412.0,
          250.0
        ],
        [
          414.0,
          250.0
        ],
        [
          414.0,
          249.0
        ],
        [
          416.0,
          247.0
        ],
        [
          417.0,
          247.0
        ],
        [
          420.0,
          244.0
        ],
        [
          421.0,
          244.0
        ],
        [
          422.0,
          243.0
        ],
        [
          423.0,
          243.0
        ],
        [
          424.0,
          242.0
        ],
        [
          424.0,
          241.0
        ],
        [
          425.0,
          240.0
        ],
        [
          425.0,
          233.0
        ],
        [
          424.0,
          232.0
        ],
        [
          424.0,
          231.0
        ]
      ],
      "group_id": null,
      "description": "",
      "difficult": false,
      "shape_type": "polygon",
      "flags": {},
      "attributes": {}
    }
  ],
  "imagePath": "170924589-25.bmp",
  "imageData": null,
  "imageHeight": 500,
  "imageWidth": 1300,
  "text": ""
}