{
  "annotations": [
    {
      "segmentation": {
        "counts": [
          186970,
          1,
          187481,
          10,
          187992,
          19,
          188502,
          29,
          189013,
          39,
          189524,
          48,
          190044,
          48,
          190564,
          48,
          191084,
          48,
          191604,
          48,
          192125,
          47,
          192645,
          47,
          193165,
          48,
          193685,
          48,
          194205,
          48,
          194725,
          48,
          195245,
          48,
          195765,
          48,
          196285,
          48,
          196805,
          48,
          197326,
          48,
          197846,
          48,
          198366,
          48,
          198886,
          48,
          199406,
          48,
          199926,
          48,
          200446,
          48,
          200966,
          48,
          201486,
          49,
          202007,
          48,
          202527,
          48,
          203047,
          48,
          203567,
          48,
          204087,
          48,
          204607,
          48,
          205127,
          48,
          205647,
          49,
          206167,
          49,
          206688,
          48,
          207208,
          48,
          207728,
          48,
          208248,
          48,
          208768,
          48,
          209288,
          48,
          209808,
          49,
          210328,
          49,
          210848,
          49,
          211368,
          49,
          211889,
          39,
          212409,
          29,
          212929,
          20,
          213449,
          10,
          213969,
          1
        ],
        "size": [
          520,
          520
        ]
      },
      "area": 2266,
      "label": "xinpian",
      "image_id": "144629311-106_defect_2_xinpian",
      "uncertain_iou": 1.0
    }
  ]
}