{
  "annotations": [
    {
      "segmentation": {
        "counts": [
          17122,
          2,
          17633,
          16,
          17650,
          2,
          18153,
          20,
          18673,
          21,
          19193,
          21,
          19714,
          20,
          20234,
          20,
          20754,
          20,
          21275,
          19,
          21795,
          19,
          22315,
          19,
          22835,
          20,
          23355,
          20,
          23875,
          19,
          24395,
          19,
          24915,
          19,
          25435,
          19,
          25955,
          18,
          26475,
          14,
          26995,
          13,
          27515,
          12,
          28035,
          11,
          28556,
          9,
          29078,
          6
        ],
        "size": [
          520,
          520
        ]
      },
      "area": 398,
      "label": "zangwuqingwei",
      "image_id": "144641466-166_defect_2_zangwuqingwei",
      "uncertain_iou": 1.0
    }
  ]
}