{
  "annotations": [
    {
      "segmentation": {
        "counts": [
          15285,
          1,
          15799,
          16,
          16312,
          33,
          16829,
          80,
          17346,
          84,
          17864,
          88,
          18381,
          92,
          18898,
          97,
          19417,
          99,
          19937,
          101,
          20456,
          103,
          20975,
          106,
          21495,
          107,
          22014,
          110,
          22533,
          111,
          23053,
          111,
          23572,
          112,
          24091,
          113,
          24610,
          114,
          25130,
          114,
          25649,
          115,
          26168,
          103,
          26688,
          90,
          27207,
          78,
          27725,
          67,
          28243,
          63,
          28761,
          59,
          29278,
          57,
          29796,
          53,
          30314,
          49,
          30832,
          48,
          31349,
          49,
          31865,
          50,
          32382,
          50,
          32899,
          51,
          33416,
          51,
          33932,
          53,
          34449,
          53,
          34967,
          53,
          35485,
          53,
          36003,
          52,
          36521,
          52,
          37039,
          52,
          37557,
          52,
          38075,
          51,
          38593,
          51,
          39113,
          49,
          39632,
          48,
          40152,
          46,
          40671,
          45,
          41191,
          43,
          41711,
          41,
          42230,
          40,
          42750,
          37,
          43270,
          35,
          43789,
          34,
          44309,
          32,
          44828,
          31,
          45348,
          29,
          45868,
          27,
          46387,
          27,
          46907,
          26,
          47426,
          26,
          47946,
          25,
          48466,
          24,
          48986,
          23,
          49506,
          21,
          50026,
          20,
          50546,
          19,
          51066,
          18,
          51586,
          17,
          52106,
          16,
          52626,
          15,
          53146,
          14,
          53666,
          13,
          54187,
          11,
          54707,
          11,
          55227,
          10,
          55747,
          9,
          56267,
          8,
          56787,
          7,
          57307,
          7,
          57827,
          6,
          58347,
          5,
          58867,
          5,
          59387,
          4,
          59907,
          4,
          60428,
          3,
          60948,
          3,
          61469,
          1,
          61989,
          1
        ],
        "size": [
          520,
          520
        ]
      },
      "area": 4283,
      "label": "toumingjiao",
      "image_id": "145734710-192_defect_4_toumingjiao",
      "uncertain_iou": 1.0
    }
  ]
}