{
  "annotations": [
    {
      "segmentation": {
        "counts": [
          138468,
          1,
          138988,
          6,
          139508,
          11,
          140028,
          11,
          140548,
          12,
          141068,
          12,
          141590,
          7,
          142111,
          1
        ],
        "size": [
          520,
          520
        ]
      },
      "area": 61,
      "label": "baiwu",
      "image_id": "161934077-36_defect_6_baiwu",
      "uncertain_iou": 1.0
    }
  ]
}