{
  "annotations": [
    {
      "segmentation": {
        "counts": [
          206863,
          1,
          207377,
          8,
          207891,
          15,
          208410,
          17,
          208928,
          20,
          209447,
          21,
          209966,
          23,
          210485,
          25,
          211003,
          28,
          211522,
          30,
          212041,
          32,
          212560,
          34,
          213078,
          37,
          213597,
          38,
          214116,
          40,
          214635,
          42,
          215154,
          27,
          215183,
          15,
          215674,
          25,
          215705,
          14,
          216193,
          24,
          216226,
          13,
          216712,
          23,
          216747,
          13,
          217231,
          22,
          217267,
          13,
          217750,
          21,
          217788,
          13,
          218272,
          17,
          218308,
          13,
          218793,
          14,
          218829,
          13,
          219315,
          7,
          219349,
          13,
          219836,
          1,
          219870,
          13,
          220390,
          13,
          220910,
          14,
          221431,
          13,
          221951,
          14,
          222472,
          13,
          222992,
          13,
          223513,
          13,
          224033,
          13,
          224554,
          12,
          225074,
          12,
          225595,
          12,
          226116,
          11,
          226637,
          10,
          227157,
          11,
          227678,
          10,
          228199,
          9,
          228719,
          9,
          229240,
          9,
          229761,
          8,
          230282,
          5,
          230802,
          4,
          231323,
          1
        ],
        "size": [
          520,
          520
        ]
      },
      "area": 954,
      "label": "zangwuyanzhong",
      "image_id": "161935210-47_defect_4_zangwuyanzhong",
      "uncertain_iou": 1.0
    }
  ]
}