{
  "annotations": [
    {
      "segmentation": {
        "counts": [
          179877,
          6,
          180364,
          1,
          180385,
          25,
          180881,
          53,
          181401,
          53,
          181921,
          53,
          182441,
          54,
          182961,
          54,
          183481,
          35,
          183526,
          8,
          184005,
          29,
          184528,
          18
        ],
        "size": [
          520,
          520
        ]
      },
      "area": 389,
      "label": "anlie",
      "image_id": "161942907-96_defect_0_anlie",
      "uncertain_iou": 1.0
    }
  ]
}