{
  "annotations": [
    {
      "segmentation": {
        "counts": [
          56684,
          15,
          56701,
          1,
          57124,
          19,
          57564,
          21,
          58004,
          22,
          58444,
          23,
          58884,
          23,
          59324,
          23,
          59764,
          19,
          59785,
          2,
          60205,
          15,
          60645,
          14,
          61086,
          3,
          61091,
          8,
          61534,
          1
        ],
        "size": [
          440,
          440
        ]
      },
      "area": 209,
      "label": "zangwuqingwei",
      "image_id": "165935_002_defect_2_zangwuqingwei",
      "uncertain_iou": 1.0
    }
  ]
}