{
  "annotations": [
    {
      "segmentation": {
        "counts": [
          150547,
          6,
          151067,
          7,
          151587,
          7,
          152108,
          7,
          152628,
          7,
          153148,
          8,
          153669,
          7,
          154189,
          7,
          154710,
          7,
          155230,
          8,
          155750,
          10,
          156271,
          10,
          156791,
          11,
          157311,
          13,
          157832,
          13,
          158352,
          14,
          158872,
          15,
          159393,
          15,
          159913,
          15,
          160433,
          16,
          160954,
          15,
          161475,
          14,
          161995,
          14,
          162515,
          14,
          163036,
          12,
          163556,
          11,
          164076,
          10,
          164597,
          8,
          165117,
          7,
          165638,
          4
        ],
        "size": [
          518,
          520
        ]
      },
      "area": 312,
      "label": "jiaotifabai",
      "image_id": "1701673317(26)_defect_2_jiaotifabai",
      "uncertain_iou": 1.0
    }
  ]
}