{
  "annotations": [
    {
      "segmentation": {
        "counts": [
          208846,
          10,
          209366,
          10,
          209886,
          10,
          210405,
          11,
          210925,
          11,
          211445,
          11,
          211965,
          11,
          212484,
          12,
          213004,
          12,
          213522,
          13,
          214041,
          14,
          214559,
          15,
          215077,
          16,
          215596,
          16,
          216116,
          16,
          216635,
          16,
          217154,
          16,
          217673,
          17,
          218193,
          16,
          218712,
          17,
          219231,
          17,
          219750,
          18,
          220270,
          17,
          220789,
          18,
          221308,
          19,
          221825,
          21,
          222343,
          23,
          222860,
          25,
          223379,
          26,
          223898,
          26,
          224416,
          27,
          224935,
          28,
          225455,
          27,
          225975,
          26,
          226495,
          25,
          227015,
          25,
          227536,
          23,
          228056,
          22,
          228576,
          21,
          229096,
          20,
          229616,
          18,
          230137,
          16,
          230658,
          14,
          231179,
          12,
          231699,
          9,
          232220,
          5,
          232741,
          1
        ],
        "size": [
          518,
          520
        ]
      },
      "area": 799,
      "label": "jiaotifabai",
      "image_id": "1701673317(43)_defect_0_jiaotifabai",
      "uncertain_iou": 1.0
    }
  ]
}