{
  "annotations": [
    {
      "segmentation": {
        "counts": [
          226960,
          1,
          227462,
          26,
          227534,
          10,
          227982,
          32,
          228045,
          20,
          228501,
          40,
          228556,
          30,
          229021,
          85,
          229540,
          87,
          230060,
          88,
          230579,
          90,
          231099,
          91,
          231618,
          93,
          232138,
          93,
          232658,
          94,
          233177,
          96,
          233697,
          97,
          234216,
          99,
          234736,
          100,
          235256,
          100,
          235775,
          102,
          236295,
          103,
          236815,
          104,
          237334,
          105,
          237854,
          106,
          238373,
          27,
          238403,
          78,
          238893,
          25,
          238924,
          78,
          239417,
          18,
          239445,
          78,
          239940,
          13,
          239966,
          77,
          240464,
          6,
          240488,
          76,
          240987,
          1,
          241009,
          76,
          241530,
          54,
          242051,
          42,
          242572,
          31
        ],
        "size": [
          520,
          520
        ]
      },
      "area": 2572,
      "label": "toumingjiao",
      "image_id": "1702625126(30)_defect_3_toumingjiao",
      "uncertain_iou": 1.0
    }
  ]
}