{
  "annotations": [
    {
      "segmentation": {
        "counts": [
          192825,
          1,
          193345,
          2,
          193864,
          4,
          194384,
          5,
          194903,
          6,
          195423,
          7,
          195942,
          9,
          196462,
          10,
          196981,
          12,
          197501,
          12,
          198019,
          13,
          198538,
          14,
          199056,
          16,
          199575,
          17,
          200093,
          18,
          200612,
          19,
          201130,
          21,
          201648,
          23,
          202167,
          23,
          202685,
          25,
          203204,
          26,
          203722,
          28,
          204240,
          30,
          204759,
          31,
          205277,
          33,
          205796,
          34,
          206314,
          36,
          206833,
          38,
          207351,
          40,
          207869,
          42,
          208388,
          43,
          208906,
          45,
          209425,
          46,
          209943,
          48,
          210461,
          50,
          210980,
          51,
          211498,
          53,
          212017,
          54,
          212535,
          56,
          213053,
          59,
          213572,
          60,
          214090,
          62,
          214609,
          63,
          215127,
          65,
          215645,
          67,
          216164,
          66,
          216682,
          67,
          217201,
          66,
          217719,
          67,
          218237,
          67,
          218754,
          69,
          219272,
          69,
          219789,
          71,
          220307,
          71,
          220825,
          72,
          221342,
          74,
          221860,
          76,
          222378,
          77,
          222895,
          80,
          223413,
          81,
          223930,
          84,
          224448,
          85,
          224964,
          89,
          225479,
          93,
          225995,
          97,
          226510,
          101,
          227026,
          104,
          227547,
          103,
          228067,
          102,
          228588,
          101,
          229108,
          100,
          229629,
          99,
          230149,
          98,
          230670,
          97,
          231190,
          96,
          231711,
          95,
          232231,
          94,
          232752,
          93,
          233273,
          91,
          233794,
          90,
          234315,
          89,
          234836,
          87,
          235356,
          87,
          235877,
          86,
          236398,
          85,
          236919,
          83,
          237440,
          82,
          237964,
          78,
          238488,
          74,
          239012,
          69,
          239535,
          66,
          240059,
          62,
          240583,
          57,
          241107,
          52,
          241632,
          46,
          242156,
          41,
          242680,
          36
        ],
        "size": [
          520,
          520
        ]
      },
      "area": 5582,
      "label": "toumingjiao",
      "image_id": "1702625126(10)_defect_1_toumingjiao",
      "uncertain_iou": 1.0
    }
  ]
}