{
  "annotations": [
    {
      "segmentation": {
        "counts": [
          99133,
          3,
          99652,
          5,
          100170,
          8,
          100689,
          10,
          101209,
          11,
          101729,
          11,
          102248,
          11,
          102768,
          11,
          103287,
          11,
          103807,
          9,
          104326,
          9,
          104845,
          9,
          105364,
          9,
          105883,
          9,
          106402,
          9,
          106921,
          9,
          107441,
          7,
          107960,
          7,
          108480,
          7,
          108999,
          7,
          109518,
          7,
          110037,
          7,
          110556,
          8,
          111075,
          8,
          111594,
          8,
          112114,
          7,
          112632,
          8,
          113151,
          8,
          113671,
          7,
          114190,
          8,
          114709,
          8,
          115228,
          8,
          115747,
          7,
          116266,
          8,
          116785,
          8,
          117304,
          8,
          117823,
          8,
          118342,
          8,
          118861,
          8,
          119380,
          8,
          119899,
          8,
          120418,
          8,
          120937,
          8,
          121456,
          8,
          121975,
          8,
          122494,
          8,
          123013,
          8,
          123532,
          9,
          124052,
          8,
          124571,
          8,
          125090,
          8,
          125609,
          8,
          126129,
          7,
          126648,
          7,
          127166,
          8,
          127686,
          8,
          128204,
          9,
          128724,
          8,
          129243,
          8,
          129762,
          8,
          130281,
          8,
          130800,
          8,
          131319,
          8,
          131838,
          8,
          132357,
          8,
          132876,
          8,
          133395,
          8,
          133914,
          8,
          134434,
          7,
          134953,
          7,
          135472,
          7,
          135991,
          7,
          136509,
          9,
          137029,
          8,
          137548,
          8,
          138067,
          8,
          138586,
          8,
          139106,
          7,
          139625,
          7,
          140144,
          7,
          140663,
          7,
          141182,
          7,
          141701,
          7,
          142220,
          7,
          142739,
          7,
          143258,
          8,
          143777,
          8,
          144296,
          8,
          144815,
          8,
          145334,
          8,
          145854,
          7,
          146373,
          7,
          146892,
          7,
          147411,
          7,
          147930,
          7,
          148449,
          8,
          148968,
          8,
          149487,
          9,
          150007,
          8,
          150526,
          7,
          151044,
          8,
          151564,
          7,
          152083,
          8,
          152602,
          8,
          153122,
          7,
          153641,
          7,
          154160,
          7,
          154679,
          7,
          155198,
          7,
          155717,
          8,
          156236,
          8,
          156755,
          8,
          157274,
          7,
          157792,
          9,
          158311,
          9,
          158830,
          9,
          159350,
          8,
          159869,
          8,
          160388,
          7,
          160906,
          9,
          161425,
          9,
          161943,
          10,
          162462,
          10,
          162980,
          11,
          163500,
          10,
          164019,
          10,
          164539,
          9,
          165058,
          10,
          165578,
          10,
          166097,
          11,
          166617,
          10,
          167137,
          10,
          167658,
          7,
          168181,
          1
        ],
        "size": [
          520,
          520
        ]
      },
      "area": 1075,
      "label": "xian",
      "image_id": "1702516271(20)_defect_0_xian",
      "uncertain_iou": 1.0
    }
  ]
}