{
  "annotations": [
    {
      "segmentation": {
        "counts": [
          155174,
          11,
          155612,
          13,
          156051,
          13,
          156489,
          14,
          156927,
          13,
          157365,
          15,
          157804,
          15,
          158242,
          16,
          158681,
          16,
          159121,
          16,
          159560,
          16,
          160000,
          15,
          160440,
          14,
          160879,
          15,
          161319,
          15,
          161759,
          14,
          162199,
          15,
          162639,
          15,
          163079,
          15,
          163519,
          15,
          163959,
          15,
          164399,
          15,
          164839,
          15,
          165279,
          15,
          165719,
          15,
          166159,
          15,
          166599,
          15,
          167039,
          15,
          167479,
          15,
          167919,
          15,
          168359,
          15,
          168799,
          15,
          169239,
          15,
          169679,
          15,
          170119,
          15,
          170559,
          15,
          170999,
          14,
          171439,
          14,
          171880,
          12,
          172321,
          9
        ],
        "size": [
          440,
          440
        ]
      },
      "area": 580,
      "label": "zangwuyanzhong",
      "image_id": "170842_885_defect_1_zangwuyanzhong",
      "uncertain_iou": 1.0
    }
  ]
}