{
  "annotations": [
    {
      "segmentation": {
        "counts": [
          348606,
          58,
          349906,
          58,
          351206,
          58,
          352506,
          58,
          353806,
          58,
          355106,
          58,
          356406,
          58,
          357706,
          58,
          359006,
          58,
          360306,
          58,
          361606,
          58,
          362906,
          58,
          364206,
          58,
          365506,
          58,
          366806,
          58,
          368106,
          58,
          369406,
          58,
          370706,
          58,
          372006,
          58,
          373306,
          58,
          374606,
          58,
          375906,
          58,
          377206,
          58,
          378506,
          58,
          379806,
          58,
          381106,
          58,
          382406,
          58,
          383706,
          58,
          385006,
          58,
          386306,
          58,
          387606,
          58,
          388906,
          58,
          390206,
          58,
          391506,
          58,
          392806,
          58,
          394106,
          58,
          395406,
          58,
          396706,
          58,
          398006,
          58,
          399306,
          58,
          400606,
          58,
          401906,
          58,
          403206,
          58,
          404506,
          58,
          405806,
          58,
          407106,
          58,
          408406,
          58,
          409706,
          58,
          411006,
          58,
          412306,
          58,
          413606,
          57,
          414906,
          57,
          416206,
          57,
          417506,
          57,
          418806,
          56,
          420106,
          56,
          421406,
          55,
          422706,
          55,
          424006,
          54,
          425306,
          54
        ],
        "size": [
          500,
          1300
        ]
      },
      "area": 3458,
      "label": "xinpian",
      "image_id": "170925682-40_defect_0_xinpian",
      "uncertain_iou": 1.0
    }
  ]
}