{
  "annotations": [
    {
      "segmentation": {
        "counts": [
          537006,
          4,
          538304,
          9,
          539603,
          12,
          540903,
          13,
          542202,
          15,
          543502,
          15,
          544802,
          15,
          546103,
          14,
          547403,
          14,
          548703,
          14,
          550004,
          13,
          551304,
          13,
          552605,
          12,
          553905,
          11,
          555206,
          10,
          556507,
          7,
          557809,
          3
        ],
        "size": [
          500,
          1300
        ]
      },
      "area": 194,
      "label": "zangwuqingwei",
      "image_id": "170932470-121_defect_3_zangwuqingwei",
      "uncertain_iou": 1.0
    }
  ]
}