{
  "annotations": [
    {
      "segmentation": {
        "counts": [
          525872,
          17,
          525902,
          5,
          527150,
          63,
          528447,
          73,
          529746,
          76,
          531045,
          78,
          532345,
          79,
          533644,
          79,
          534944,
          79,
          536244,
          79,
          537544,
          79,
          538844,
          79,
          540145,
          78,
          541446,
          76,
          542747,
          75,
          544047,
          75,
          545348,
          74,
          546650,
          71,
          547953,
          68,
          549256,
          63,
          550558,
          54,
          551860,
          49,
          553163,
          35,
          553202,
          4,
          554468,
          25,
          555776,
          13
        ],
        "size": [
          500,
          1300
        ]
      },
      "area": 1546,
      "label": "zangwuyanzhong",
      "image_id": "170923484-11_defect_4_zangwuyanzhong",
      "uncertain_iou": 1.0
    }
  ]
}