{
  "annotations": [
    {
      "segmentation": {
        "counts": [
          136177,
          1,
          136697,
          2,
          137216,
          4,
          137736,
          5,
          138256,
          6,
          138775,
          8,
          139295,
          9,
          139815,
          9,
          140334,
          10,
          140854,
          10,
          141374,
          10,
          141894,
          10,
          142413,
          11,
          142933,
          11,
          143453,
          11,
          143972,
          13,
          144492,
          13,
          145012,
          13,
          145531,
          14,
          146051,
          14,
          146571,
          14,
          147090,
          15,
          147610,
          15,
          148130,
          15,
          148649,
          15,
          149169,
          15,
          149689,
          14,
          150208,
          15,
          150728,
          15,
          151248,
          14,
          151768,
          14,
          152287,
          15,
          152807,
          14,
          153327,
          14,
          153846,
          14,
          154366,
          14,
          154886,
          14,
          155405,
          14,
          155925,
          14,
          156445,
          13,
          156964,
          14,
          157484,
          14,
          158004,
          13,
          158523,
          14,
          159043,
          14,
          159563,
          13,
          160082,
          14,
          160602,
          13,
          161122,
          13,
          161641,
          14,
          162161,
          13,
          162681,
          13,
          163201,
          12,
          163720,
          13,
          164240,
          13,
          164760,
          12,
          165279,
          13,
          165799,
          13,
          166319,
          12,
          166838,
          13,
          167358,
          12,
          167877,
          13,
          168397,
          13,
          168916,
          13,
          169436,
          13,
          169955,
          13,
          170475,
          13,
          170994,
          14,
          171513,
          14,
          172033,
          14,
          172552,
          15,
          173072,
          14,
          173591,
          15,
          174110,
          15,
          174630,
          15,
          175149,
          16,
          175669,
          15,
          176188,
          16,
          176708,
          15,
          177227,
          16,
          177746,
          16,
          178266,
          16,
          178785,
          16,
          179305,
          16,
          179824,
          16,
          180343,
          17,
          180863,
          16,
          181382,
          17,
          181902,
          16,
          182421,
          17,
          182941,
          16,
          183460,
          17,
          183979,
          17,
          184499,
          17,
          185018,
          17,
          185538,
          17,
          186057,
          17,
          186577,
          17,
          187096,
          17,
          187615,
          18,
          188135,
          17,
          188654,
          18,
          189174,
          17,
          189693,
          18,
          190212,
          19,
          190732,
          18,
          191251,
          19,
          191771,
          18,
          192290,
          19,
          192810,
          18,
          193329,
          19,
          193848,
          19,
          194368,
          19,
          194887,
          19,
          195407,
          19,
          195926,
          19,
          196445,
          20,
          196965,
          19,
          197484,
          20,
          198004,
          19,
          198523,
          20,
          199043,
          19,
          199562,
          20,
          200081,
          20,
          200601,
          20,
          201120,
          20,
          201640,
          20,
          202159,
          20,
          202678,
          21,
          203198,
          20,
          203717,
          21,
          204237,
          20,
          204756,
          21,
          205276,
          20,
          205795,
          21,
          206315,
          20,
          206834,
          21,
          207354,
          20,
          207874,
          20,
          208393,
          20,
          208913,
          20,
          209432,
          20,
          209952,
          20,
          210471,
          20,
          210991,
          20,
          211511,
          19,
          212030,
          19,
          212550,
          19,
          213069,
          19,
          213589,
          19,
          214109,
          18,
          214628,
          19,
          215148,
          18,
          215667,
          19,
          216187,
          18,
          216706,
          19,
          217226,
          18,
          217746,
          18,
          218266,
          17,
          218787,
          14,
          219307,
          12,
          219827,
          10,
          220347,
          8,
          220868,
          5,
          221388,
          3,
          221908,
          1
        ],
        "size": [
          520,
          520
        ]
      },
      "area": 2540,
      "label": "zangwuqingwei",
      "image_id": "1713518018(6)_defect_1_zangwuqingwei",
      "uncertain_iou": 1.0
    }
  ]
}