{
  "annotations": [
    {
      "segmentation": {
        "counts": [
          89073,
          1,
          89592,
          3,
          90111,
          5,
          90631,
          6,
          91150,
          8,
          91669,
          10,
          92190,
          10,
          92711,
          10,
          93231,
          11,
          93752,
          11,
          94273,
          11,
          94794,
          10,
          95315,
          10,
          95836,
          10,
          96357,
          10,
          96878,
          10,
          97399,
          9,
          97919,
          10,
          98440,
          9,
          98961,
          9,
          99482,
          9,
          100002,
          10,
          100523,
          10,
          101044,
          10,
          101565,
          9,
          102086,
          9,
          102606,
          10,
          103127,
          9,
          103648,
          9,
          104169,
          8,
          104689,
          8,
          105210,
          7,
          105730,
          7,
          106251,
          6,
          106771,
          6,
          107291,
          6,
          107811,
          6,
          108331,
          6,
          108851,
          6,
          109371,
          5,
          109891,
          5,
          110411,
          4,
          110931,
          4
        ],
        "size": [
          520,
          520
        ]
      },
      "area": 342,
      "label": "mao",
      "image_id": "1715158793(30)_defect_0_mao",
      "uncertain_iou": 1.0
    }
  ]
}