{
  "annotations": [
    {
      "segmentation": {
        "counts": [
          105113,
          1,
          105632,
          3,
          106152,
          4,
          106672,
          4,
          107191,
          5,
          107711,
          5,
          108230,
          6,
          108750,
          6,
          109270,
          4
        ],
        "size": [
          520,
          520
        ]
      },
      "area": 38,
      "label": "zazhi",
      "image_id": "1731058384(5)_defect_2_zazhi",
      "uncertain_iou": 1.0
    }
  ]
}