{
  "annotations": [
    {
      "segmentation": {
        "counts": [
          170499,
          1,
          171018,
          2,
          171538,
          2,
          172057,
          3,
          172576,
          3,
          173096,
          3,
          173615,
          4,
          174134,
          5,
          174654,
          5,
          175173,
          6,
          175692,
          7,
          176212,
          6,
          176731,
          7,
          177250,
          8,
          177770,
          8,
          178289,
          9,
          178808,
          10,
          179328,
          10,
          179847,
          11,
          180367,
          10,
          180886,
          11,
          181406,
          11,
          181925,
          12,
          182444,
          13,
          182964,
          12,
          183483,
          13,
          184003,
          12,
          184522,
          13,
          185042,
          12,
          185561,
          13,
          186080,
          13,
          186600,
          13,
          187119,
          13,
          187638,
          14,
          188157,
          14,
          188677,
          14,
          189196,
          14,
          189715,
          15,
          190234,
          16,
          190754,
          15,
          191273,
          16,
          191792,
          16,
          192311,
          17,
          192831,
          16,
          193350,
          17,
          193869,
          17,
          194388,
          18,
          194908,
          17,
          195427,
          18,
          195946,
          18,
          196465,
          19,
          196985,
          18,
          197504,
          19,
          198023,
          19,
          198543,
          18,
          199062,
          19,
          199581,
          19,
          200101,
          18,
          200620,
          18,
          201139,
          19,
          201658,
          19,
          202178,
          18,
          202697,
          18,
          203216,
          19,
          203735,
          19,
          204254,
          19,
          204773,
          19,
          205292,
          20,
          205811,
          20,
          206330,
          20,
          206849,
          20,
          207368,
          21,
          207887,
          21,
          208406,
          21,
          208925,
          21,
          209444,
          22,
          209963,
          22,
          210482,
          22,
          211001,
          22,
          211520,
          23,
          212039,
          23,
          212558,
          23,
          213077,
          23,
          213596,
          24,
          214115,
          24,
          214634,
          24,
          215153,
          24,
          215672,
          25,
          216191,
          25,
          216710,
          25,
          217229,
          25,
          217748,
          26,
          218267,
          26,
          218786,
          26,
          219305,
          26,
          219824,
          27,
          220342,
          28,
          220861,
          28,
          221379,
          29,
          221898,
          29,
          222416,
          30,
          222935,
          30,
          223453,
          31,
          223972,
          31,
          224490,
          32,
          225009,
          32,
          225527,
          33,
          226046,
          33,
          226564,
          33,
          227083,
          33,
          227601,
          34,
          228119,
          35,
          228637,
          36,
          229156,
          36,
          229674,
          37,
          230192,
          38,
          230710,
          39,
          231228,
          40,
          231747,
          40,
          232265,
          40,
          232783,
          40,
          233299,
          42,
          233815,
          44,
          234330,
          47,
          234846,
          49,
          235362,
          51,
          235879,
          52,
          236395,
          54,
          236912,
          55,
          237428,
          56,
          237945,
          55,
          238461,
          56,
          238978,
          55,
          239494,
          56,
          240011,
          56,
          240528,
          55,
          241045,
          55,
          241562,
          51,
          242079,
          48,
          242596,
          44,
          243131,
          23,
          243666,
          1
        ],
        "size": [
          520,
          520
        ]
      },
      "area": 3393,
      "label": "yijiao",
      "image_id": "173458827-12_defect_3_yijiao",
      "uncertain_iou": 1.0
    }
  ]
}