{
  "annotations": [
    {
      "segmentation": {
        "counts": [
          236387,
          18,
          236904,
          21,
          237420,
          25,
          237936,
          29,
          238454,
          31,
          238974,
          31,
          239494,
          30,
          240014,
          30,
          240534,
          30,
          241059,
          24,
          241586,
          17,
          242109,
          13,
          242630,
          12,
          243150,
          11,
          243671,
          9,
          244192,
          7,
          244714,
          3
        ],
        "size": [
          520,
          520
        ]
      },
      "area": 341,
      "label": "zangwuqingwei",
      "image_id": "173552794-24_defect_1_zangwuqingwei",
      "uncertain_iou": 1.0
    }
  ]
}