{
  "annotations": [
    {
      "segmentation": {
        "counts": [
          158572,
          1,
          159092,
          1,
          159612,
          1,
          160131,
          3,
          160651,
          3,
          161171,
          3,
          161691,
          3,
          162211,
          4,
          162730,
          5,
          163250,
          5,
          163770,
          5,
          164290,
          5,
          164809,
          6,
          165329,
          6,
          165849,
          6,
          166369,
          6,
          166889,
          6,
          167409,
          6,
          167929,
          6,
          168449,
          6,
          168969,
          6,
          169488,
          7,
          170008,
          7,
          170528,
          7,
          171048,
          7,
          171568,
          7,
          172088,
          7,
          172608,
          7,
          173128,
          7,
          173648,
          7,
          174168,
          7,
          174688,
          7,
          175208,
          7,
          175728,
          7,
          176248,
          7,
          176768,
          7,
          177288,
          7,
          177808,
          7,
          178328,
          7,
          178848,
          7,
          179368,
          7,
          179888,
          7,
          180408,
          7,
          180928,
          7,
          181448,
          7,
          181968,
          7,
          182488,
          7,
          183008,
          7,
          183528,
          7,
          184048,
          7,
          184568,
          7,
          185087,
          8,
          185607,
          8,
          186127,
          8,
          186647,
          8,
          187166,
          9,
          187686,
          9,
          188206,
          9,
          188726,
          9,
          189246,
          9,
          189765,
          10,
          190285,
          10,
          190805,
          9,
          191325,
          9,
          191845,
          9,
          192364,
          10,
          192884,
          10,
          193404,
          10,
          193924,
          10,
          194443,
          11,
          194963,
          11,
          195483,
          11,
          196003,
          11,
          196524,
          10,
          197044,
          10,
          197564,
          10,
          198084,
          10,
          198605,
          9,
          199125,
          9,
          199645,
          9,
          200165,
          9,
          200685,
          9,
          201205,
          9,
          201725,
          9,
          202245,
          9,
          202765,
          9,
          203286,
          8,
          203806,
          8,
          204326,
          8,
          204846,
          8,
          205366,
          8,
          205886,
          8,
          206406,
          8,
          206926,
          8,
          207446,
          8,
          207966,
          8,
          208487,
          7,
          209007,
          7,
          209527,
          7,
          210047,
          7,
          210567,
          7,
          211088,
          6,
          211608,
          6,
          212128,
          6,
          212648,
          6,
          213168,
          6,
          213689,
          5,
          214209,
          5,
          214729,
          5,
          215250,
          4,
          215770,
          4,
          216291,
          3,
          216811,
          3,
          217332,
          2,
          217852,
          2,
          218373,
          1
        ],
        "size": [
          520,
          520
        ]
      },
      "area": 811,
      "label": "posun",
      "image_id": "173546504-21_defect_6_posun",
      "uncertain_iou": 1.0
    }
  ]
}