{
  "annotations": [
    {
      "segmentation": {
        "counts": [
          40172,
          8,
          40690,
          12,
          41209,
          14,
          41728,
          16,
          42248,
          17,
          42767,
          31,
          42810,
          5,
          43287,
          32,
          43328,
          7,
          43806,
          34,
          43846,
          8,
          44326,
          36,
          44364,
          9,
          44845,
          47,
          45365,
          46,
          45884,
          45,
          46404,
          43,
          46923,
          43,
          47442,
          42,
          47960,
          40,
          48480,
          38,
          48999,
          38,
          49519,
          37,
          50038,
          37,
          50558,
          35,
          51077,
          35,
          51597,
          34,
          52117,
          32,
          52636,
          31,
          53156,
          29,
          53676,
          28,
          54196,
          26,
          54716,
          25,
          55236,
          24,
          55756,
          22,
          56276,
          21,
          56796,
          19,
          57316,
          19,
          57837,
          17,
          58357,
          15,
          58877,
          15,
          59397,
          14,
          59917,
          13,
          60437,
          11,
          60957,
          10,
          61478,
          7,
          61998,
          6,
          62520,
          2
        ],
        "size": [
          520,
          520
        ]
      },
      "area": 1175,
      "label": "tuhei",
      "image_id": "1_1-204_defect_0_tuhei",
      "uncertain_iou": 1.0
    }
  ]
}