{
  "annotations": [
    {
      "segmentation": {
        "counts": [
          86677,
          6,
          87076,
          7,
          87475,
          9,
          87874,
          10,
          88275,
          10,
          88676,
          9,
          89077,
          9,
          89480,
          6,
          89882,
          3,
          90284,
          1
        ],
        "size": [
          400,
          400
        ]
      },
      "area": 70,
      "label": "zazhi",
      "image_id": "1_1-3999998888687 (10)_defect_5_zazhi",
      "uncertain_iou": 1.0
    }
  ]
}