{
  "annotations": [
    {
      "segmentation": {
        "counts": [
          141972,
          1,
          142371,
          5,
          142769,
          7,
          143168,
          8,
          143568,
          9,
          143967,
          10,
          144367,
          10,
          144766,
          11,
          145166,
          11,
          145566,
          11,
          145966,
          11,
          146365,
          12,
          146765,
          12,
          147165,
          12,
          147565,
          12,
          147965,
          12,
          148365,
          12,
          148765,
          12,
          149175,
          1
        ],
        "size": [
          400,
          400
        ]
      },
      "area": 179,
      "label": "posun",
      "image_id": "1_1-3999998888687 (45)_defect_2_posun",
      "uncertain_iou": 1.0
    }
  ]
}