{
  "annotations": [
    {
      "segmentation": {
        "counts": [
          56040,
          1,
          56440,
          5,
          56840,
          6,
          57240,
          7,
          57641,
          8,
          58041,
          9,
          58441,
          9,
          58841,
          10,
          59243,
          8,
          59644,
          8,
          60046,
          6,
          60447,
          4,
          60849,
          1
        ],
        "size": [
          400,
          400
        ]
      },
      "area": 82,
      "label": "zangwuqingwei",
      "image_id": "1_1-3999998888687 (53)_defect_4_zangwuqingwei",
      "uncertain_iou": 1.0
    }
  ]
}