{
  "annotations": [
    {
      "segmentation": {
        "counts": [
          124648,
          38,
          125168,
          38,
          125688,
          38,
          126208,
          38,
          126728,
          38,
          127248,
          38,
          127768,
          39,
          128288,
          39,
          128808,
          39,
          129328,
          39,
          129848,
          39,
          130368,
          39,
          130888,
          39,
          131408,
          39,
          131928,
          39,
          132448,
          39,
          132968,
          39,
          133489,
          38,
          134009,
          39,
          134529,
          39,
          135049,
          39,
          135569,
          39,
          136089,
          39,
          136609,
          39,
          137129,
          39,
          137649,
          39,
          138169,
          39,
          138689,
          39,
          139209,
          39,
          139729,
          39,
          140249,
          40,
          140769,
          40,
          141289,
          40,
          141809,
          40,
          142329,
          40,
          142888,
          1
        ],
        "size": [
          520,
          520
        ]
      },
      "area": 1364,
      "label": "xinpian",
      "image_id": "1_1-39_defect_1_xinpian",
      "uncertain_iou": 1.0
    }
  ]
}