{
  "annotations": [
    {
      "segmentation": {
        "counts": [
          23675,
          1,
          24195,
          7,
          24715,
          10,
          25235,
          13,
          25755,
          15,
          26274,
          18,
          26794,
          21,
          27314,
          23,
          27834,
          28,
          28354,
          31,
          28880,
          27,
          29410,
          20,
          29935,
          10,
          30460,
          1
        ],
        "size": [
          520,
          520
        ]
      },
      "area": 225,
      "label": "zangwuyanzhong",
      "image_id": "1_1-74_defect_3_zangwuyanzhong",
      "uncertain_iou": 1.0
    }
  ]
}